flower/urls.py
flower/settings.py
flower/events.py
flower/__main__.py
flower/app.py
flower/command.py
flower/__init__.py
flower/templates/broker.html
flower/templates/base.html
flower/templates/navbar.html
flower/templates/task.html
flower/templates/dashboard.html
flower/templates/tasks.html
flower/templates/monitor.html
flower/templates/worker.html
flower/templates/404.html
flower/templates/error.html
flower/views/auth.py
flower/views/workers.py
flower/views/tasks.py
flower/views/monitor.py
flower/views/error.py
flower/views/dashboard.py
flower/views/broker.py
flower/views/__init__.py
flower/utils/template.py
flower/utils/tasks.py
flower/utils/broker.py
flower/utils/__init__.py
flower/static/favicon.ico
flower/static/css/bootstrap.min.css
flower/static/css/jquery-ui.css
flower/static/css/bootstrap.css
flower/static/css/bootstrap-responsive.css
flower/static/css/rickshaw.min.css
flower/static/css/bootstrap-responsive.min.css
flower/static/css/flower.css
flower/static/img/apple-touch-icon-72-precomposed.png
flower/static/img/glyphicons-halflings-white.png
flower/static/img/apple-touch-icon-57-precomposed.png
flower/static/img/apple-touch-icon-144-precomposed.png
flower/static/img/glyphicons-halflings.png
flower/static/img/apple-touch-icon-114-precomposed.png
flower/static/js/d3.min.js
flower/static/js/jquery-1.7.2.min.js
flower/static/js/bootstrap.js
flower/static/js/flower.js
flower/static/js/d3.layout.min.js
flower/static/js/bootstrap-dropdown.js
flower/static/js/bootstrap-carousel.js
flower/static/js/bootstrap.min.js
flower/static/js/bootstrap-scrollspy.js
flower/static/js/bootstrap-collapse.js
flower/static/js/bootstrap-modal.js
flower/static/js/jquery-ui-1-8-15.min.js
flower/static/js/bootstrap-popover.js
flower/static/js/bootstrap-typeahead.js
flower/static/js/bootstrap-transition.js
flower/static/js/bootstrap-alert.js
flower/static/js/bootstrap-tooltip.js
flower/static/js/bootstrap-tab.js
flower_new-0.8.0.dist-info/metadata.json
flower_new-0.8.0.dist-info/RECORD
flower_new-0.8.0.dist-info/entry_points.txt
flower_new-0.8.0.dist-info/top_level.txt
flower_new-0.8.0.dist-info/DESCRIPTION.rst
flower_new-0.8.0.dist-info/METADATA
flower_new-0.8.0.dist-info/WHEEL
