Metadata-Version: 2.0
Name: flower-new
Version: 0.8.0
Summary: Celery Flower
Home-page: https://github.com/mher/flower
Author: Mher Movsisyan
Author-email: mher.movsisyan@gmail.com
License: BSD
Platform: UNKNOWN
Classifier: Development Status :: 4 - Beta
Classifier: Intended Audience :: Developers
Classifier: License :: OSI Approved :: BSD License
Classifier: Topic :: System :: Distributed Computing
Classifier: Programming Language :: Python
Classifier: Programming Language :: Python :: 2
Classifier: Programming Language :: Python :: 2.7
Classifier: Programming Language :: Python :: 3
Classifier: Programming Language :: Python :: 3.3
Classifier: Programming Language :: Python :: 3.4
Classifier: Programming Language :: Python :: Implementation :: CPython
Classifier: Operating System :: OS Independent
Requires-Dist: celery
Requires-Dist: tornado (>=3.2.0)
Requires-Dist: babel
